Tabla1.3/tabla1e3.v
module gateLevel(input wire A, B, C, D, output Y);

	wire w1, w2, w3, w4, w5, w6, w7, w8, w9, w10, w11, w12;
	not(w1, A);
	not(w2, B);
	not(w3, C);
	not(w4, D);
	and(w5, w1, w2, w3, w4);
	and(w6, A, B, w3, w4);
	and(w7, w1, B, w3, D);
	and(w8, A, w2, w3, D);
	and(w9, w1, w2, C, D);
	and(w10, A, B, C, D);
	and(w11, w1, B, C, w4);
	and(w12, A, w2, C, w4);
	or(Y, w5, w6, w7, w8, w9, w10, w11, w12);
	
endmodule

module operadores(input wire A, B, C, D, output Y);

	assign Y=(~A&~B&~C&~D) | (A&B&~C&~D) | (~A&B&~C&D) | (A&~B&~C&D) | (~A&~B&C&D) | (A&B&C&D) |(~A&B&C&~D) | (A&~B&C&~D);

endmodule

Tabla1.3/tabla1e3_tb.v
module testbench();

	reg p1, p2, p3, p4, p5, p6, p7, p8;
	wire led1, led2;
	
	gateLevel   G1(p1, p2, p3, p4, led1);
	operadores OP1(p5, p6, p7, p8, led2);
	
	initial begin
		$display("A B C D | Y");
		$display("--------|--");
		$monitor("%b %b %b | %b", p1, p2, p3, led1);
		p1=0; p2=0; p3=0; p4=0;
		#1 p1=0; p2=0; p3=0; p4=1;
		#1 p1=0; p2=0; p3=1; p4=0;
		#1 p1=0; p2=0; p3=1; p4=1;
		#1 p1=0; p2=1; p3=0; p4=0;
		#1 p1=0; p2=1; p3=0; p4=1;
		#1 p1=0; p2=1; p3=1; p4=0;
		#1 p1=0; p2=1; p3=1; p4=1;
		#1 p1=1; p2=0; p3=0; p4=0;
		#1 p1=1; p2=0; p3=0; p4=1;
		#1 p1=1; p2=0; p3=1; p4=0;
		#1 p1=1; p2=0; p3=1; p4=1;
		#1 p1=1; p2=1; p3=0; p4=0;
		#1 p1=1; p2=1; p3=0; p4=1;
		#1 p1=1; p2=1; p3=1; p4=0;
		#1 p1=1; p2=1; p3=1; p4=1;
		
		end 

	initial
		#20 $finish;
		
	initial begin
		$dumpfile("tabla1e3_tb.vcd");
		$dumpvars(0, testbench);
		end	

endmodule

Tabla1.3/tabla1e3_tb.vcd
$date
	Fri Aug 07 18:05:17 2020
$end
$version
	Icarus Verilog
$end
$timescale
	1ps
$end
$scope module testbench $end
$var wire 1 ! led2 $end
$var wire 1 " led1 $end
$var reg 1 # p1 $end
$var reg 1 $ p2 $end
$var reg 1 % p3 $end
$var reg 1 & p4 $end
$var reg 1 ' p5 $end
$var reg 1 ( p6 $end
$var reg 1 ) p7 $end
$var reg 1 * p8 $end
$scope module G1 $end
$var wire 1 # A $end
$var wire 1 $ B $end
$var wire 1 % C $end
$var wire 1 & D $end
$var wire 1 " Y $end
$var wire 1 + w1 $end
$var wire 1 , w10 $end
$var wire 1 - w11 $end
$var wire 1 . w12 $end
$var wire 1 / w2 $end
$var wire 1 0 w3 $end
$var wire 1 1 w4 $end
$var wire 1 2 w5 $end
$var wire 1 3 w6 $end
$var wire 1 4 w7 $end
$var wire 1 5 w8 $end
$var wire 1 6 w9 $end
$upscope $end
$scope module OP1 $end
$var wire 1 ' A $end
$var wire 1 ( B $end
$var wire 1 ) C $end
$var wire 1 * D $end
$var wire 1 ! Y $end
$upscope $end
$upscope $end
$enddefinitions $end
#0
$dumpvars
06
05
04
03
12
11
10
1/
0.
0-
0,
1+
x*
x)
x(
x'
0&
0%
0$
0#
1"
x!
$end
#1
0"
02
01
1&
#2
11
00
0&
1%
#3
1"
01
16
1&
#4
0"
11
10
06
0/
0&
0%
1$
#5
1"
01
14
1&
#6
1"
1-
11
04
00
0&
1%
#7
0"
0-
01
1&
#8
11
10
1/
0+
0&
0%
0$
1#
#9
1"
01
15
1&
#10
1"
1.
11
05
00
0&
1%
#11
0"
0.
01
1&
#12
1"
13
11
10
0/
0&
0%
1$
#13
0"
03
01
1&
#14
11
00
0&
1%
#15
1"
01
1,
1&
